InformativeUninformativeFrameClassifier/__init__.py
InformativeUninformativeFrameClassifier/inference.py
InformativeUninformativeFrameClassifier/model_functions.py
InformativeUninformativeFrameClassifier/mydataset.py
InformativeUninformativeFrameClassifier/randomaug.py
InformativeUninformativeFrameClassifier/run.py
InformativeUninformativeFrameClassifier/sampler.py
InformativeUninformativeFrameClassifier/test.py
InformativeUninformativeFrameClassifier/train.py
InformativeUninformativeFrameClassifier/visualise_data.py
InformativeUninformativeFrameClassifier-0.0.1.dist-info/LICENSE
InformativeUninformativeFrameClassifier-0.0.1.dist-info/METADATA
InformativeUninformativeFrameClassifier-0.0.1.dist-info/WHEEL
InformativeUninformativeFrameClassifier-0.0.1.dist-info/top_level.txt
InformativeUninformativeFrameClassifier-0.0.1.dist-info/RECORD
