Metadata-Version: 2.1
Name: InformativeUninformativeFrameClassifier
Version: 0.0.1
Summary: Python module to train and test informative/uninformative frames on Cholect80 and HeiCo datasets.
Home-page: https://github.com/HassnaIrzan/InformativeUninformativeFrameClassifier
Author: Hassna Irzan
Author-email: rmaphir@gmail.com
License: MIT License
Platform: UNKNOWN
Requires-Dist: numpy
Requires-Dist: torch
Requires-Dist: torchvision
Requires-Dist: timm
Requires-Dist: tensorboard
Requires-Dist: sklearn
Requires-Dist: pillow
Requires-Dist: natsort
